<?xml version="1.0" encoding="UTF-8"?><frequencies xmlns:t="http://www.tei-c.org/ns/1.0"><lemma form="biti" freq="27010"/>
     <lemma form="imeti" freq="21283"/>
     <lemma form="vedeti" freq="15086"/>
     <lemma form="priti" freq="14520"/>
     <lemma form="hoteti" freq="13584"/>
     <lemma form="iti" freq="13446"/>
     <lemma form="moči" freq="12600" inner="y"/>
     <lemma form="videti" freq="12574"/>
     <lemma form="morati" freq="11180" inner="y"/>
     <lemma form="reči" freq="9863"/>
     <lemma form="govoriti" freq="9027"/>
     <lemma form="misliti" freq="8063"/>
     <lemma form="gledati" freq="7473"/>
     <lemma form="dati" freq="6911"/>
     <lemma form="povedati" freq="6224"/>
     <lemma form="praviti" freq="5787"/>
     <lemma form="stati" freq="5404"/>
     <lemma form="vprašati" freq="5324"/>
     <lemma form="pogledati" freq="4599"/>
     <lemma form="ostati" freq="4528"/>
     <lemma form="dejati" freq="4470"/>
     <lemma form="začeti" freq="4439"/>
     <lemma form="zdeti" freq="4271"/>
     <lemma form="stopiti" freq="4067"/>
     <lemma form="poznati" freq="4039"/>
     <lemma form="vzeti" freq="3976"/>
     <lemma form="storiti" freq="3855"/>
     <lemma form="sedeti" freq="3793"/>
     <lemma form="slišati" freq="3777"/>
     <lemma form="dobiti" freq="3691"/>
     <lemma form="odgovoriti" freq="3672"/>
     <lemma form="ljubiti" freq="3518"/>
     <lemma form="čakati" freq="3503"/>
     <lemma form="hoditi" freq="3431"/>
     <lemma form="delati" freq="3387"/>
     <lemma form="smeti" freq="3235"/>
     <lemma form="prositi" freq="3204"/>
     <lemma form="živeti" freq="3065"/>
     <lemma form="oditi" freq="2980"/>
     <lemma form="čutiti" freq="2972"/>
     <lemma form="vrniti" freq="2943"/>
     <lemma form="najti" freq="2871"/>
     <lemma form="bati" freq="2824"/>
     <lemma form="postati" freq="2733"/>
     <lemma form="obrniti" freq="2693"/>
     <lemma form="pomagati" freq="2633"/>
     <lemma form="pustiti" freq="2566"/>
     <lemma form="meniti" freq="2565"/>
     <lemma form="poslušati" freq="2497"/>
     <lemma form="znati" freq="2452"/>
     <lemma form="ležati" freq="2403"/>
     <lemma form="pokazati" freq="2305"/>
     <lemma form="iskati" freq="2284"/>
     <lemma form="pozabiti" freq="2211"  inner="y"/>
     <lemma form="spoznati" freq="2198"  inner="y"/>
     <lemma form="odpreti" freq="2177"/>
     <lemma form="upati" freq="2130"/>
     <lemma form="prihajati" freq="2032"/>
     <lemma form="zgoditi" freq="1993"/>
     <lemma form="smejati" freq="1939"/>
     <lemma form="želeti" freq="1928"/>
     <lemma form="prinesti" freq="1915"/>
     <lemma form="vstati" freq="1902"/>
     <lemma form="molčati" freq="1868"  inner="y"/>
     <lemma form="pasti" freq="1860"/>
     <lemma form="držati" freq="1843"/>
     <lemma form="ozreti" freq="1840"/>
     <lemma form="čuti" freq="1787"/>
     <lemma form="kazati" freq="1775"/>
     <lemma form="pisati" freq="1772"/>
     <lemma form="hiteti" freq="1763"/>
     <lemma form="umreti" freq="1749"/>
     <lemma form="dvigniti" freq="1744"/>
     <lemma form="prijeti" freq="1737"/>
     <lemma form="pripovedovati" freq="1726"/>
     <lemma form="braniti" freq="1685"/>
     <lemma form="zapustiti" freq="1670"/>
     <lemma form="razumeti" freq="1659"  inner="y"/>
     <lemma form="rešiti" freq="1634"/>
     <lemma form="nositi" freq="1611"/>
     <lemma form="klicati" freq="1608"/>
     <lemma form="poslati" freq="1608"/>
     <lemma form="vzklikniti" freq="1558"/>
     <lemma form="verjeti" freq="1551"/>
     <lemma form="izginiti" freq="1524"/>
     <lemma form="piti" freq="1515"/>
     <lemma form="spraviti" freq="1509"/>
     <lemma form="zagledati" freq="1488"/>
     <lemma form="vreči" freq="1473"/>
     <lemma form="nadaljevati" freq="1467"/>
     <lemma form="ustaviti" freq="1460"/>
     <lemma form="spati" freq="1397"/>
     <lemma form="spregovoriti" freq="1324"/>
     <lemma form="udariti" freq="1293"/>
     <lemma form="pričakovati" freq="1287" inner="m"/>
     <lemma form="napraviti" freq="1281"/>
     <lemma form="postaviti" freq="1274"/>
     <lemma form="zapaziti" freq="1230"/>
     <lemma form="izgubiti" freq="1212"/>
     <lemma form="skleniti" freq="1203"/>
     <lemma form="bežati" freq="1199"/>
     <lemma form="dajati" freq="1180"/>
     <lemma form="spomniti" freq="1177"/>
     <lemma form="potegniti" freq="1159"/>
     <lemma form="motiti" freq="1153"/>
     <lemma form="goditi" freq="1153"/>
     <lemma form="veseliti" freq="1152"/>
     <lemma form="zaklicati" freq="1151"/>
     <lemma form="skrbeti" freq="1147"  inner="y"/>
     <lemma form="zvedeti" freq="1140"/>
     <lemma form="pričeti" freq="1135"/>
     <lemma form="skočiti" freq="1130"/>
     <lemma form="zreti" freq="1125"/>
     <lemma form="jeti" freq="1124"/>
     <lemma form="zadeti" freq="1123"/>
     <lemma form="brati" freq="1104"/>
     <lemma form="odgovarjati" freq="1094"/>
     <lemma form="zahtevati" freq="1081"/>
     <lemma form="bližati" freq="1078"/>
     <lemma form="sesti" freq="1076"/>
     <lemma form="položiti" freq="1075"/>
     <lemma form="odvrniti" freq="1065"/>
     <lemma form="čuditi" freq="1063"/>
     <lemma form="trpeti" freq="1058" inner="m"/>
     <lemma form="oglasiti" freq="1053"/>
     <lemma form="voditi" freq="1051"/>
     <lemma form="siliti" freq="1046"/>
     <lemma form="stopati" freq="1040"/>
     <lemma form="zapreti" freq="1028"/>
     <lemma form="spominjati" freq="1017"/>
     <lemma form="imenovati" freq="1013"/>
     <lemma form="moliti" freq="1009"/>
     <lemma form="teči" freq="1006"/>
     <lemma form="igrati" freq="1003"/>
     <lemma form="stisniti" freq="1000"/>
     <lemma form="narediti" freq="1000"/>
     <lemma form="peljati" freq="982"/>
     <lemma form="vleči" freq="980"/>
     <lemma form="opaziti" freq="980"  inner="y"/>
     <lemma form="soditi" freq="976"/>
     <lemma form="seči" freq="964"/>
     <lemma form="goreti" freq="957"/>
     <lemma form="pomisliti" freq="951"/>
     <lemma form="jokati" freq="943"/>
     <lemma form="obljubiti" freq="930"/>
     <lemma form="sprejeti" freq="926"/>
     <lemma form="tresti" freq="924"/>
     <lemma form="pozdraviti" freq="916"/>
     <lemma form="učiti" freq="911"/>
     <lemma form="pristaviti" freq="908"/>
     <lemma form="peti" freq="904"/>
     <lemma form="marati" freq="899"/>
     <lemma form="plačati" freq="898"/>
     <lemma form="kričati" freq="895"/>
     <lemma form="opraviti" freq="890"/>
     <lemma form="poklicati" freq="882"/>
     <lemma form="pripeljati" freq="863"/>
     <lemma form="potrebovati" freq="853"/>
     <lemma form="poljubiti" freq="845"/>
     <lemma form="slutiti" freq="840"/>
     <lemma form="trditi" freq="834"/>
     <lemma form="zasmejati" freq="830"/>
     <lemma form="izvedeti" freq="828"/>
     <lemma form="podati" freq="822"/>
     <lemma form="opazovati" freq="821"/>
     <lemma form="šepetati" freq="818"/>
     <lemma form="utegniti" freq="815"/>
     <lemma form="vstopiti" freq="808"/>
     <lemma form="nasmehniti" freq="804"/>
     <lemma form="počakati" freq="797"/>
     <lemma form="izročiti" freq="790"/>
     <lemma form="ozirati" freq="786"/>
     <lemma form="jeziti" freq="785"/>
     <lemma form="nesti" freq="783"/>
     <lemma form="ravnati" freq="783"/>
     <lemma form="srečati" freq="783"/>
     <lemma form="obstati" freq="779"/>
     <lemma form="svetiti" freq="761"/>
     <lemma form="spremeniti" freq="760"/>
     <lemma form="dovoliti" freq="759"/>
     <lemma form="jesti" freq="749"/>
     <lemma form="umakniti" freq="749"/>
     <lemma form="objeti" freq="745"/>
     <lemma form="doseči" freq="744"/>
     <lemma form="posloviti" freq="739"/>
     <lemma form="vzdihniti" freq="733"/>
     <lemma form="paziti" freq="731"/>
     <lemma form="planiti" freq="730"/>
     <lemma form="vračati" freq="726"/>
     <lemma form="pripraviti" freq="717"/>
     <lemma form="prikazati" freq="712"/>
     <lemma form="zanimati" freq="711"/>
     <lemma form="ugajati" freq="707"/>
     <lemma form="ločiti" freq="707"/>
     <lemma form="prašati" freq="707"/>
     <lemma form="približati" freq="705"/>
     <lemma form="sanjati" freq="703"  inner="m"/>
     <lemma form="zaupati" freq="701" inner="m"/>
     <lemma form="tolažiti" freq="699"/>
     <lemma form="premišljevati" freq="695"/>
     <lemma form="čitati" freq="694"/>
     <lemma form="pridobiti" freq="692"/>
     <lemma form="odpustiti" freq="692"/>
     <lemma form="odpeljati" freq="688"/>
     <lemma form="uiti" freq="683"/>
     <lemma form="izdati" freq="679"/>
     <lemma form="veleti" freq="674"/>
     <lemma form="miniti" freq="673"/>
     <lemma form="muditi" freq="671"/>
     <lemma form="naznaniti" freq="670"/>
     <lemma form="ukazati" freq="663"/>
     <lemma form="viseti" freq="663"/>
     <lemma form="zgrabiti" freq="662"/>
     <lemma form="očitati" freq="657"/>
     <lemma form="pomeniti" freq="657"/>
     <lemma form="dvigati" freq="648"/>
     <lemma form="kupiti" freq="644"/>
     <lemma form="zameriti" freq="644"/>
     <lemma form="skrivati" freq="641"/>
     <lemma form="prevzeti" freq="640"/>
     <lemma form="vzdigniti" freq="637"/>
     <lemma form="premagati" freq="635"/>
     <lemma form="vpiti" freq="628"/>
     <lemma form="odločiti" freq="628"  inner="y"/>
     <lemma form="prepričati" freq="625"/>
     <lemma form="ujeti" freq="623"/>
     <lemma form="boleti" freq="618"/>
     <lemma form="pobrati" freq="613"/>
     <lemma form="ponuditi" freq="608"/>
     <lemma form="umeti" freq="608"/>
     <lemma form="začuditi" freq="608"/>
     <lemma form="služiti" freq="608"/>
     <lemma form="nastati" freq="608"/>
     <lemma form="veljati" freq="607"/>
     <lemma form="zaviti" freq="606"/>
     <lemma form="skriti" freq="601"/>
     <lemma form="prestrašiti" freq="594"/>
     <lemma form="uživati" freq="594"/>
     <lemma form="poiskati" freq="593"/>
     <lemma form="postajati" freq="591"/>
     <lemma form="brigati" freq="583"/>
     <lemma form="izpustiti" freq="577"/>
     <lemma form="oprostiti" freq="577"/>
     <lemma form="povrniti" freq="576"/>
     <lemma form="ugovarjati" freq="576"/>
     <lemma form="pripravljati" freq="574"/>
     <lemma form="posrečiti" freq="573"/>
     <lemma form="zaslužiti" freq="567"/>
     <lemma form="odpraviti" freq="567"/>
     <lemma form="dospeti" freq="565"/>
     <lemma form="ganiti" freq="562"/>
     <lemma form="končati" freq="557"/>
     <lemma form="naročiti" freq="554"/>
     <lemma form="verovati" freq="553"/>
     <lemma form="jemati" freq="550"/>
     <lemma form="varovati" freq="549"/>
     <lemma form="slediti" freq="549"/>
     <lemma form="vdati" freq="548"/>
     <lemma form="obiskati" freq="547"/>
     <lemma form="voziti" freq="544"/>
     <lemma form="zapeti" freq="544"/>
     <lemma form="plesati" freq="543"/>
     <lemma form="zaspati" freq="542"/>
     <lemma form="rasti" freq="542"/>
     <lemma form="tožiti" freq="539"/>
     <lemma form="ubiti" freq="537"/>
     <lemma form="stiskati" freq="536"/>
     <lemma form="padati" freq="536"/>
     <lemma form="izpolniti" freq="533"/>
     <lemma form="zmeniti" freq="532"/>
     <lemma form="izbrati" freq="532"/>
     <lemma form="ponavljati" freq="531"/>
     <lemma form="nasloniti" freq="529"/>
     <lemma form="trepetati" freq="528" inner="m"/>
     <lemma form="skloniti" freq="527"/>
     <lemma form="povabiti" freq="524"/>
     <lemma form="mrmrati" freq="521"/>
     <lemma form="gnati" freq="521"/>
     <lemma form="spremljati" freq="518"/>
     <lemma form="hvaliti" freq="516"/>
     <lemma form="vabiti" freq="510"/>
     <lemma form="počivati" freq="510"/>
     <lemma form="vladati" freq="509"/>
     <lemma form="spustiti" freq="507"/>
     <lemma form="sloneti" freq="502"/>
     <lemma form="stresti" freq="501"/>
     <lemma form="pritisniti" freq="500"/>
     <lemma form="zganiti" freq="500"/>
     <lemma form="napasti" freq="498"/>
     <lemma form="mučiti" freq="497"/>
     <lemma form="napotiti" freq="494"/>
     <lemma form="zavrniti" freq="493"/>
     <lemma form="spremiti" freq="490"/>
     <lemma form="poskusiti" freq="487"/>
     <lemma form="roditi" freq="486"/>
     <lemma form="stanovati" freq="482"/>
     <lemma form="priznati" freq="481"/>
     <lemma form="vesti" freq="477"/>
     <lemma form="pritrditi" freq="475"/>
     <lemma form="prodati" freq="475"/>
     <lemma form="strmeti" freq="475"/>
     <lemma form="zbrati" freq="473"/>
     <lemma form="zbuditi" freq="472"/>
     <lemma form="truditi" freq="469"/>
     <lemma form="odriniti" freq="466"/>
     <lemma form="razodeti" freq="466"/>
     <lemma form="sijati" freq="464"/>
     <lemma form="svetovati" freq="462"/>
     <lemma form="tičati" freq="462"/>
     <lemma form="sovražiti" freq="460" inner="m"/>
     <lemma form="zahajati" freq="460"/>
     <lemma form="leči" freq="460"/>
     <lemma form="vzbuditi" freq="456"/>
     <lemma form="nagniti" freq="456"/>
     <lemma form="loviti" freq="454"/>
     <lemma form="pogovarjati" freq="453"/>
     <lemma form="šteti" freq="451"/>
     <lemma form="zakričati" freq="450"/>
     <lemma form="ogledati" freq="450"/>
     <lemma form="pozdravljati" freq="449"/>
     <lemma form="odpirati" freq="446"/>
     <lemma form="odhajati" freq="442"/>
     <lemma form="odnesti" freq="441"/>
     <lemma form="premisliti" freq="438"/>
     <lemma form="boriti" freq="435"/>
     <lemma form="omeniti" freq="434"/>
     <lemma form="zaslišati" freq="433"/>
     <lemma form="kreniti" freq="433"/>
     <lemma form="ogledovati" freq="432"/>
     <lemma form="zbirati" freq="432"/>
     <lemma form="upreti" freq="432"/>
     <lemma form="dam" freq="431"/>
     <lemma form="staviti" freq="431"/>
     <lemma form="obetati" freq="430"/>
     <lemma form="pridružiti" freq="429"/>
     <lemma form="dotakniti" freq="428"/>
     <lemma form="domisliti" freq="427"/>
     <lemma form="bivati" freq="427"/>
     <lemma form="dozdevati" freq="426"/>
     <lemma form="popraviti" freq="421"/>
     <lemma form="privoščiti" freq="419"/>
     <lemma form="korakati" freq="416"/>
     <lemma form="ustavljati" freq="416"/>
     <lemma form="ponoviti" freq="413"/>
     <lemma form="izvršiti" freq="410"/>
     <lemma form="izpraševati" freq="409"/>
     <lemma form="pognati" freq="409"/>
     <lemma form="zabavati" freq="409"/>
     <lemma form="pričati" freq="407"/>
     <lemma form="smehljati" freq="407"/>
     <lemma form="uničiti" freq="405"/>
     <lemma form="pomiriti" freq="403"/>
     <lemma form="lotiti" freq="400"/>
     <lemma form="doživeti" freq="400"/>
     <lemma form="početi" freq="400"/>
     <lemma form="zahvaliti" freq="398"/>
     <lemma form="plavati" freq="397"/>
     <lemma form="tikati" freq="393"/>
     <lemma form="premišljati" freq="392"/>
     <lemma form="naučiti" freq="391"/>
     <lemma form="potrkati" freq="389"/>
     <lemma form="ubogati" freq="388"/>
     <lemma form="posvetiti" freq="386"/>
     <lemma form="potolažiti" freq="385"/>
     <lemma form="sporočiti" freq="384"/>
     <lemma form="vezati" freq="383"/>
     <lemma form="širiti" freq="383"/>
     <lemma form="zmagati" freq="382"/>
     <lemma form="okleniti" freq="381"/>
     <lemma form="pobegniti" freq="379"/>
     <lemma form="skušati" freq="379"/>
     <lemma form="razložiti" freq="378"/>
     <lemma form="usmiliti" freq="378"/>
     <lemma form="prihiteti" freq="377"/>
     <lemma form="vzdihovati" freq="376"/>
     <lemma form="zavedati" freq="375"/>
     <lemma form="ogibati" freq="374"/>
     <lemma form="zavpiti" freq="373"/>
     <lemma form="pogrešati" freq="373"/>
     <lemma form="uganiti" freq="373"/>
     <lemma form="zbežati" freq="372"/>
     <lemma form="razlagati" freq="371"/>
     <lemma form="pripetiti" freq="370"/>
     <lemma form="poročiti" freq="367"/>
     <lemma form="hrepeneti" freq="367" inner="m"/>
     <lemma form="meriti" freq="366"/>
     <lemma form="porabiti" freq="366"/>
     <lemma form="obiti" freq="364"/>
     <lemma form="pripomniti" freq="363"/>
     <lemma form="obesiti" freq="362"/>
     <lemma form="lagati" freq="362"/>
     <lemma form="zibati" freq="362"/>
     <lemma form="upirati" freq="361"/>
     <lemma form="umolkniti" freq="360"/>
     <lemma form="dostaviti" freq="359"/>
     <lemma form="ohraniti" freq="359"/>
     <lemma form="manjkati" freq="358"/>
     <lemma form="opravljati" freq="356"/>
     <lemma form="maščevati" freq="356"/>
     <lemma form="jezditi" freq="355"/>
     <lemma form="plačevati" freq="354"/>
     <lemma form="kaznovati" freq="352"/>
     <lemma form="vstajati" freq="351"/>
     <lemma form="odmevati" freq="351"/>
     <lemma form="izkušati" freq="349"/>
     <lemma form="zgruditi" freq="349"/>
     <lemma form="dokazati" freq="348"/>
     <lemma form="streljati" freq="347"/>
     <lemma form="prodajati" freq="346"/>
     <lemma form="odložiti" freq="346"/>
     <lemma form="metati" freq="345"/>
     <lemma form="žaliti" freq="342"/>
     <lemma form="nameravati" freq="342" inner="y"/>
     <lemma form="prebuditi" freq="341"/>
     <lemma form="peči" freq="340"/>
     <lemma form="sukati" freq="340"/>
     <lemma form="šumeti" freq="340"/>
     <lemma form="smatrati" freq="340"/>
     <lemma form="ponujati" freq="339"/>
     <lemma form="polastiti" freq="338"/>
     <lemma form="začutiti" freq="338"/>
     <lemma form="povesiti" freq="338"/>
     <lemma form="streči" freq="335"/>
     <lemma form="segati" freq="334"/>
     <lemma form="nadejati" freq="332"/>
     <lemma form="ugibati" freq="331"/>
     <lemma form="zapisati" freq="328"/>
     <lemma form="izreči" freq="328"/>
     <lemma form="dvomiti" freq="328"/>
     <lemma form="trajati" freq="327"/>
     <lemma form="začuti" freq="326"/>
     <lemma form="urediti" freq="322"/>
     <lemma form="šiniti" freq="321"/>
     <lemma form="žrtvovati" freq="321"/>
     <lemma form="preživeti" freq="320"/>
     <lemma form="pristopiti" freq="320"/>
     <lemma form="priseči" freq="319"/>
     <lemma form="prenašati" freq="319"/>
     <lemma form="pojaviti" freq="319"/>
     <lemma form="zakriti" freq="319"/>
     <lemma form="spoštovati" freq="318"/>
     <lemma form="tiščati" freq="317"/>
     <lemma form="sklepati" freq="317"/>
     <lemma form="usesti" freq="317"/>
     <lemma form="izgovoriti" freq="316"/>
     <lemma form="opomniti" freq="316"/>
     <lemma form="privesti" freq="315"/>
     <lemma form="rabiti" freq="315"/>
     <lemma form="varati" freq="314"/>
     <lemma form="dihati" freq="314"/>
     <lemma form="zasvetiti" freq="314"/>
     <lemma form="zardeti" freq="313"/>
     <lemma form="objemati" freq="313"/>
     <lemma form="ugledati" freq="312"/>
     <lemma form="prikloniti" freq="312"/>
     <lemma form="obračati" freq="312"/>
     <lemma form="potrditi" freq="309"/>
     <lemma form="vtakniti" freq="308"/>
     <lemma form="odkriti" freq="308"/>
     <lemma form="utihniti" freq="308"/>
     <lemma form="gibati" freq="308"/>
     <lemma form="vpraševati" freq="307"/>
     <lemma form="jahati" freq="307"/>
     <lemma form="vršiti" freq="307"/>
     <lemma form="pošiljati" freq="306"/>
     <lemma form="tajiti" freq="306"/>
     <lemma form="omahniti" freq="305"/>
     <lemma form="razveseliti" freq="305"/>
     <lemma form="povzeti" freq="303"/>
     <lemma form="poditi" freq="303"/>
     <lemma form="poročati" freq="301"/>
     <lemma form="pregnati" freq="301"/>
     <lemma form="stokati" freq="301"/>
     <lemma form="glasiti" freq="299"/>
     <lemma form="prepustiti" freq="299"/>
     <lemma form="šaliti" freq="299"/>
     <lemma form="sramovati" freq="299"/>
     <lemma form="spodobiti" freq="298"/>
     <lemma form="trgati" freq="297"/>
     <lemma form="obleči" freq="297"/>
     <lemma form="čuvati" freq="296"/>
     <lemma form="pretiti" freq="296"/>
     <lemma form="umirati" freq="295"/>
     <lemma form="nahajati" freq="293"/>
     <lemma form="žareti" freq="291"/>
     <lemma form="umoriti" freq="290"/>
     <lemma form="vplivati" freq="288"/>
     <lemma form="bojevati" freq="288"/>
     <lemma form="lesti" freq="287"/>
     <lemma form="sniti" freq="286"/>
     <lemma form="odvesti" freq="286"/>
     <lemma form="pobiti" freq="285"/>
     <lemma form="zavzeti" freq="285"/>
     <lemma form="poseči" freq="284"/>
     <lemma form="preganjati" freq="283"/>
     <lemma form="napolniti" freq="282"/>
     <lemma form="doneti" freq="282"/>
     <lemma form="znebiti" freq="281"/>
     <lemma form="nehati" freq="280"/>
     <lemma form="kuhati" freq="280"/>
     <lemma form="odpotovati" freq="280"/>
     <lemma form="občudovati" freq="280"/>
     <lemma form="dobivati" freq="279"/>
     <lemma form="nastopiti" freq="279"/>
     <lemma form="godrnjati" freq="279"/>
     <lemma form="ustrašiti" freq="278"/>
     <lemma form="občevati" freq="276"/>
     <lemma form="podpirati" freq="275"/>
     <lemma form="razlegati" freq="274"/>
     <lemma form="seznaniti" freq="273"/>
     <lemma form="zaiti" freq="273"/>
     <lemma form="poginiti" freq="273"/>
     <lemma form="polniti" freq="272"/>
     <lemma form="potrpeti" freq="271"/>
     <lemma form="izvoliti" freq="270"/>
     <lemma form="zazdeti" freq="270"/>
     <lemma form="okreniti" freq="269"/>
     <lemma form="deliti" freq="267"/>
     <lemma form="preskrbeti" freq="265"/>
     <lemma form="zasukati" freq="265"/>
     <lemma form="prebiti" freq="265"/>
     <lemma form="izkazati" freq="265"/>
     <lemma form="razgovarjati" freq="265"/>
     <lemma form="poljubljati" freq="265"/>
     <lemma form="umikati" freq="264"/>
     <lemma form="naveličati" freq="264"/>
     <lemma form="občutiti" freq="264"/>
     <lemma form="zamahniti" freq="263"/>
     <lemma form="iztrgati" freq="262"/>
     <lemma form="smiliti" freq="261" inner="m"/>
     <lemma form="zapomniti" freq="261"/>
     <lemma form="pomikati" freq="257"/>
     <lemma form="prikimati" freq="257"/>
     <lemma form="vrteti" freq="256"/>
     <lemma form="podreti" freq="256"/>
     <lemma form="dišati" freq="256"/>
     <lemma form="sneti" freq="256"/>
     <lemma form="prigovarjati" freq="254"/>
     <lemma form="prinašati" freq="254"/>
     <lemma form="obrisati" freq="253"/>
     <lemma form="dražiti" freq="253"/>
     <lemma form="prižgati" freq="252"/>
     <lemma form="poreči" freq="252"/>
     <lemma form="pogledovati" freq="252"/>
     <lemma form="počiti" freq="252"/>
     <lemma form="pokloniti" freq="252"/>
     <lemma form="privaditi" freq="251"/>
     <lemma form="stražiti" freq="251"/>
     <lemma form="pregledati" freq="251"/>
     <lemma form="poklekniti" freq="250"/>
     <lemma form="kleti" freq="250"/>
     <lemma form="zapoditi" freq="249"/>
     <lemma form="oženiti" freq="249"/>
     <lemma form="izpiti" freq="249"/>
     <lemma form="zatisniti" freq="248"/>
     <lemma form="ceniti" freq="247"/>
     <lemma form="zavesti" freq="247"/>
     <lemma form="spravljati" freq="247"/>
     <lemma form="napisati" freq="246"/>
     <lemma form="sprehajati" freq="246"/>
     <lemma form="zveneti" freq="246"/>
     <lemma form="zašepetati" freq="244"/>
     <lemma form="klanjati" freq="244"/>
     <lemma form="ukazovati" freq="244"/>
     <lemma form="pretresti" freq="242"/>
     <lemma form="koristiti" freq="242"/>
     <lemma form="zagnati" freq="241"/>
     <lemma form="zapirati" freq="241"/>
     <lemma form="odreči" freq="241"/>
     <lemma form="predstaviti" freq="241"/>
     <lemma form="pomniti" freq="240"/>
     <lemma form="klečati" freq="240"/>
     <lemma form="vzbujati" freq="240"/>
     <lemma form="iztegniti" freq="239"/>
     <lemma form="mahati" freq="239"/>
     <lemma form="oddahniti" freq="238"/>
     <lemma form="prejeti" freq="238"/>
     <lemma form="vneti" freq="238"/>
     <lemma form="viti" freq="238"/>
     <lemma form="motriti" freq="238"/>
     <lemma form="ugasniti" freq="237"/>
     <lemma form="gospodariti" freq="237"/>
     <lemma form="prikrivati" freq="237"/>
     <lemma form="pregovoriti" freq="237"/>
     <lemma form="svariti" freq="237"/>
     <lemma form="nadlegovati" freq="236"/>
     <lemma form="zagovarjati" freq="236"/>
     <lemma form="oglašati" freq="235"/>
     <lemma form="preseliti" freq="235"/>
     <lemma form="opozoriti" freq="235"/>
     <lemma form="prisesti" freq="234"/>
     <lemma form="odbiti" freq="234"/>
     <lemma form="častiti" freq="234"/>
     <lemma form="zasesti" freq="233"/>
     <lemma form="oteti" freq="233"/>
     <lemma form="ogovoriti" freq="233"/>
     <lemma form="predstavljati" freq="233"/>
     <lemma form="težiti" freq="232"/>
     <lemma form="izvleči" freq="232"/>
     <lemma form="odrezati" freq="231"/>
     <lemma form="raziti" freq="231"/>
     <lemma form="čepeti" freq="231"/>
     <lemma form="bosti" freq="230"/>
     <lemma form="škodovati" freq="229"/>
     <lemma form="suniti" freq="229"/>
     <lemma form="buditi" freq="229"/>
     <lemma form="združiti" freq="228"/>
     <lemma form="odpovedati" freq="228"/>
     <lemma form="prebivati" freq="228"/>
     <lemma form="steči" freq="226"/>
     <lemma form="nabrati" freq="226"/>
     <lemma form="preiti" freq="226"/>
     <lemma form="pritrjevati" freq="226"/>
     <lemma form="zamisliti" freq="225"/>
     <lemma form="zadrževati" freq="225"/>
     <lemma form="ustvariti" freq="224"/>
     <lemma form="prebledeti" freq="224"/>
     <lemma form="izgovarjati" freq="223"/>
     <lemma form="poskušati" freq="223"/>
     <lemma form="brisati" freq="220"/>
     <lemma form="velevati" freq="220"/>
     <lemma form="premagovati" freq="220"/>
     <lemma form="mešati" freq="219"/>
     <lemma form="zagrmeti" freq="219"/>
     <lemma form="plaziti" freq="218"/>
     <lemma form="pozvati" freq="218"/>
     <lemma form="pritiskati" freq="217"/>
     <lemma form="potisniti" freq="216"/>
     <lemma form="priteči" freq="216"/>
     <lemma form="kaliti" freq="216"/>
     <lemma form="postopati" freq="215"/>
     <lemma form="švigati" freq="215"/>
     <lemma form="vznemirjati" freq="215"/>
     <lemma form="pokrivati" freq="214"/>
     <lemma form="nagovoriti" freq="214"/>
     <lemma form="navdajati" freq="214"/>
     <lemma form="poravnati" freq="213"/>
     <lemma form="povzdigniti" freq="213"/>
     <lemma form="zlesti" freq="213"/>
     <lemma form="zamuditi" freq="213"/>
     <lemma form="otresti" freq="213"/>
     <lemma form="ziniti" freq="212"/>
     <lemma form="kopati" freq="212"/>
     <lemma form="zadoneti" freq="212"/>
     <lemma form="naložiti" freq="211"/>
     <lemma form="umiriti" freq="211"/>
     <lemma form="ustreliti" freq="210"/>
     <lemma form="hraniti" freq="210"/>
     <lemma form="sprevideti" freq="210"/>
     <lemma form="zamrmrati" freq="210"/>
     <lemma form="leteti" freq="209"/>
     <lemma form="pahniti" freq="209"/>
     <lemma form="prisiliti" freq="208"/>
     <lemma form="pograbiti" freq="208"/>
     <lemma form="določiti" freq="208"/>
     <lemma form="nis" freq="207"/>
     <lemma form="čestitati" freq="207"/>
     <lemma form="izviti" freq="207"/>
     <lemma form="obhajati" freq="207"/>
     <lemma form="zaigrati" freq="206"/>
     <lemma form="kaditi" freq="206"/>
     <lemma form="pokriti" freq="206"/>
     <lemma form="zadostovati" freq="206"/>
     <lemma form="pohvaliti" freq="205"/>
     <lemma form="popraševati" freq="205"/>
     <lemma form="zadušiti" freq="205"/>
     <lemma form="prestati" freq="205"/>
     <lemma form="ukrasti" freq="205"/>
     <lemma form="zašumeti" freq="205"/>
     <lemma form="izprazniti" freq="204"/>
     <lemma form="darovati" freq="201"/>
     <lemma form="napiti" freq="200"/>
     <lemma form="hudovati" freq="200"/>
     <lemma form="postreči" freq="199"/>
     <lemma form="zmotiti" freq="199"/>
     <lemma form="potovati" freq="199"/>
     <lemma form="prisegati" freq="199"/>
     <lemma form="preiskati" freq="199"/>
     <lemma form="trkati" freq="199"/>
     <lemma form="ženiti" freq="198"/>
     <lemma form="poslavljati" freq="198"/>
     <lemma form="pomoliti" freq="197"/>
     <lemma form="prepirati" freq="197"/>
     <lemma form="zasledovati" freq="197"/>
     <lemma form="nasmejati" freq="197"/>
     <lemma form="zaječati" freq="196"/>
     <lemma form="ustreči" freq="196"/>
     <lemma form="premakniti" freq="196"/>
     <lemma form="pretrgati" freq="196"/>
     <lemma form="žalovati" freq="196" inner="m"/>
     <lemma form="raztrgati" freq="195"/>
     <lemma form="uteči" freq="195"/>
     <lemma form="zapovedovati" freq="195"/>
     <lemma form="divjati" freq="195"/>
     <lemma form="obsoditi" freq="194"/>
     <lemma form="prešiniti" freq="194"/>
     <lemma form="pojasniti" freq="194"/>
     <lemma form="zapuščati" freq="193"/>
     <lemma form="rogati" freq="193"/>
     <lemma form="rezati" freq="193"/>
     <lemma form="treti" freq="193"/>
     <lemma form="popravljati" freq="192"/>
     <lemma form="vikniti" freq="192"/>
     <lemma form="razviti" freq="191"/>
     <lemma form="skakati" freq="191"/>
     <lemma form="srati" freq="191"/>
     <lemma form="spreleteti" freq="191"/>
     <lemma form="zatrjevati" freq="190"/>
     <lemma form="pokimati" freq="190"/>
     <lemma form="prekrižati" freq="189"/>
     <lemma form="izmisliti" freq="189"/>
     <lemma form="obžalovati" freq="189"/>
     <lemma form="gojiti" freq="189"/>
     <lemma form="razbiti" freq="188"/>
     <lemma form="nameniti" freq="188"/>
     <lemma form="gristi" freq="188"/>
     <lemma form="pečati" freq="187"/>
     <lemma form="begati" freq="187"/>
     <lemma form="kesati" freq="187"/>
     <lemma form="zakleniti" freq="187"/>
     <lemma form="poprašati" freq="187"/>
     <lemma form="zapovedati" freq="187"/>
     <lemma form="razširiti" freq="187"/>
     <lemma form="moleti" freq="187"/>
     <lemma form="šepniti" freq="187"/>
     <lemma form="zanašati" freq="186"/>
     <lemma form="vreti" freq="186"/>
     <lemma form="vzdramiti" freq="186"/>
     <lemma form="odstopiti" freq="186"/>
     <lemma form="oddati" freq="186"/>
     <lemma form="ukreniti" freq="185"/>
     <lemma form="povpraševati" freq="185"/>
     <lemma form="tepsti" freq="185"/>
     <lemma form="prenesti" freq="185"/>
     <lemma form="odlikovati" freq="185"/>
     <lemma form="prebrati" freq="185"/>
     <lemma form="razločiti" freq="185"/>
     <lemma form="groziti" freq="185"/>
     <lemma form="dirjati" freq="184"/>
     <lemma form="udeležiti" freq="184"/>
     <lemma form="odtrgati" freq="184"/>
     <lemma form="prileteti" freq="183"/>
     <lemma form="nastaviti" freq="183"/>
     <lemma form="pobirati" freq="183"/>
     <lemma form="prodreti" freq="182"/>
     <lemma form="norčevati" freq="182"/>
     <lemma form="premikati" freq="182"/>
     <lemma form="ostajati" freq="181"/>
     <lemma form="prenehati" freq="181"/>
     <lemma form="zakrivati" freq="181"/>
     <lemma form="slušati" freq="180"/>
     <lemma form="prestopiti" freq="180"/>
     <lemma form="zabavljati" freq="180"/>
     <lemma form="moriti" freq="180"/>
     <lemma form="ozdraveti" freq="180"/>
     <lemma form="gladiti" freq="179"/>
     <lemma form="kimati" freq="179"/>
     <lemma form="delovati" freq="179"/>
     <lemma form="rotiti" freq="179"/>
     <lemma form="privezati" freq="178"/>
     <lemma form="pogladiti" freq="178"/>
     <lemma form="opominjati" freq="178"/>
     <lemma form="pluti" freq="178"/>
     <lemma form="dreti" freq="177"/>
     <lemma form="zaškripati" freq="176"/>
     <lemma form="ihteti" freq="176"/>
     <lemma form="krikniti" freq="176"/>
     <lemma form="prežati" freq="175"/>
     <lemma form="zajokati" freq="175"/>
     <lemma form="izraziti" freq="175"/>
     <lemma form="preteči" freq="175"/>
     <lemma form="zastaviti" freq="174"/>
     <lemma form="napravljati" freq="174"/>
     <lemma form="zastokati" freq="174"/>
     <lemma form="deti" freq="174"/>
     <lemma form="prekiniti" freq="174"/>
     <lemma form="puščati" freq="173"/>
     <lemma form="prepovedati" freq="173"/>
     <lemma form="migniti" freq="172"/>
     <lemma form="zaljubiti" freq="172"/>
     <lemma form="zapeljati" freq="171"/>
     <lemma form="obotavljati" freq="171"/>
     <lemma form="jecljati" freq="171"/>
     <lemma form="naseliti" freq="171"/>
     <lemma form="posaditi" freq="170"/>
     <lemma form="zaničevati" freq="170"/>
     <lemma form="poriniti" freq="169"/>
     <lemma form="ubijati" freq="169"/>
     <lemma form="pokopati" freq="169"/>
     <lemma form="sprejemati" freq="169"/>
     <lemma form="mirovati" freq="169"/>
     <lemma form="tuliti" freq="169"/>
     <lemma form="laziti" freq="169"/>
     <lemma form="odpočiti" freq="169"/>
     <lemma form="prikupiti" freq="168"/>
     <lemma form="dokazovati" freq="168"/>
     <lemma form="naleteti" freq="168"/>
     <lemma form="dremati" freq="167"/>
     <lemma form="snubiti" freq="166"/>
     <lemma form="strašiti" freq="166"/>
     <lemma form="razburiti" freq="166"/>
     <lemma form="dodati" freq="165"/>
     <lemma form="dovršiti" freq="164"/>
     <lemma form="razdeliti" freq="164"/>
     <lemma form="zastati" freq="164"/>
     <lemma form="kovati" freq="163"/>
     <lemma form="naznanjati" freq="163"/>
     <lemma form="razvneti" freq="163"/>
     <lemma form="zaliti" freq="163"/>
     <lemma form="tolči" freq="162"/>
     <lemma form="navaditi" freq="162"/>
     <lemma form="šivati" freq="162"/>
     <lemma form="dogovoriti" freq="162"/>
     <lemma form="poskočiti" freq="162"/>
     <lemma form="oklepati" freq="162"/>
     <lemma form="odskočiti" freq="162"/>
     <lemma form="zvoniti" freq="161"/>
     <lemma form="zakriviti" freq="161"/>
     <lemma form="posvetovati" freq="161"/>
     <lemma form="zvijati" freq="161"/>
     <lemma form="preklinjati" freq="161"/>
     <lemma form="ubraniti" freq="161"/>
     <lemma form="vzpeti" freq="160"/>
     <lemma form="primerjati" freq="160"/>
     <lemma form="namigniti" freq="160"/>
     <lemma form="praznovati" freq="160"/>
     <lemma form="odtegniti" freq="160"/>
     <lemma form="zadržati" freq="160"/>
     <lemma form="obmolkniti" freq="160"/>
     <lemma form="obvarovati" freq="159"/>
     <lemma form="raznesti" freq="159"/>
     <lemma form="zanesti" freq="159"/>
     <lemma form="odhiteti" freq="159"/>
     <lemma form="obdržati" freq="158"/>
     <lemma form="spoznavati" freq="158"/>
     <lemma form="razžaliti" freq="158"/>
     <lemma form="študirati" freq="158"/>
     <lemma form="baviti" freq="157"/>
     <lemma form="modrovati" freq="157"/>
     <lemma form="meti" freq="157"/>
     <lemma form="zavidati" freq="157"/>
     <lemma form="razgrniti" freq="157"/>
     <lemma form="priskočiti" freq="157"/>
     <lemma form="valiti" freq="156"/>
     <lemma form="tarnati" freq="156"/>
     <lemma form="omožiti" freq="155"/>
     <lemma form="poplačati" freq="155"/>
     <lemma form="trčiti" freq="155"/>
     <lemma form="lesketati" freq="155"/>
     <lemma form="miriti" freq="155"/>
     <lemma form="osupniti" freq="154"/>
     <lemma form="dolgočasiti" freq="154"/>
     <lemma form="zamoči" freq="154"/>
     <lemma form="obupati" freq="153" inner="m"/>
     <lemma form="razmišljati" freq="153"/>
     <lemma form="obležati" freq="153"/>
     <lemma form="stresati" freq="153"/>
     <lemma form="zardel" freq="153"/>
     <lemma form="razjasniti" freq="153"/>
     <lemma form="škripati" freq="153"/>
     <lemma form="opravičevati" freq="152"/>
     <lemma form="zavladati" freq="152"/>
     <lemma form="izhajati" freq="152"/>
     <lemma form="čislati" freq="152"/>
     <lemma form="ječati" freq="152"/>
     <lemma form="mikati" freq="152"/>
     <lemma form="zahvaljevati" freq="152"/>
     <lemma form="preprečiti" freq="152"/>
     <lemma form="odnehati" freq="152"/>
     <lemma form="odmakniti" freq="151"/>
     <lemma form="pomoči" freq="151"/>
     <lemma form="razprostirati" freq="150"/>
     <lemma form="računati" freq="150"/>
     <lemma form="doiti" freq="150"/>
     <lemma form="ponižati" freq="150"/>
     <lemma form="oviti" freq="150"/>
     <lemma form="razkriti" freq="150"/>
     <lemma form="zvezati" freq="150"/>
     <lemma form="pogovoriti" freq="150"/>
     <lemma form="radovati" freq="149"/>
     <lemma form="zavedeti" freq="149"/>
     <lemma form="vršati" freq="149"/>
     <lemma form="utripati" freq="149"/>
     <lemma form="prizanesti" freq="149"/>
     <lemma form="ponesti" freq="148"/>
     <lemma form="slikati" freq="148"/>
     <lemma form="pohiteti" freq="148"/>
     <lemma form="kipeti" freq="148"/>
     <lemma form="zdramiti" freq="148"/>
     <lemma form="napeti" freq="148"/>
     <lemma form="privleči" freq="147"/>
     <lemma form="goniti" freq="147"/>
     <lemma form="podariti" freq="147"/>
     <lemma form="nabirati" freq="146"/>
     <lemma form="pomakniti" freq="146"/>
     <lemma form="napadati" freq="146"/>
     <lemma form="preudarjati" freq="146"/>
     <lemma form="ohladiti" freq="146"/>
     <lemma form="ubežati" freq="146"/>
     <lemma form="ostrmeti" freq="145"/>
     <lemma form="obdajati" freq="145"/>
     <lemma form="vzdigovati" freq="145"/>
     <lemma form="mahniti" freq="144"/>
     <lemma form="stradati" freq="144"/>
     <lemma form="razliti" freq="144"/>
     <lemma form="razvedriti" freq="143"/>
     <lemma form="terjati" freq="143"/>
     <lemma form="izjaviti" freq="143"/>
     <lemma form="prečitati" freq="143"/>
     <lemma form="kupovati" freq="142"/>
     <lemma form="krasti" freq="142"/>
     <lemma form="zidati" freq="142"/>
     <lemma form="podajati" freq="142"/>
     <lemma form="spreminjati" freq="142"/>
     <lemma form="zažareti" freq="142"/>
     <lemma form="treščiti" freq="141"/>
     <lemma form="spogledati" freq="141"/>
     <lemma form="sopsti" freq="141"/>
     <lemma form="odpravljati" freq="140"/>
     <lemma form="zakleti" freq="140"/>
     <lemma form="majati" freq="140"/>
     <lemma form="poprositi" freq="140"/>
     <lemma form="ustanoviti" freq="139"/>
     <lemma form="družiti" freq="139"/>
     <lemma form="vzkipeti" freq="139"/>
     <lemma form="zijati" freq="139"/>
     <lemma form="shajati" freq="139"/>
     <lemma form="prepevati" freq="139"/>
     <lemma form="krotiti" freq="139"/>
     <lemma form="vlačiti" freq="138"/>
     <lemma form="vtikati" freq="138"/>
     <lemma form="požreti" freq="138"/>
     <lemma form="točiti" freq="138"/>
     <lemma form="uvideti" freq="138"/>
     <lemma form="zdrkniti" freq="138"/>
     <lemma form="utrditi" freq="137"/>
     <lemma form="poudarjati" freq="137"/>
     <lemma form="liti" freq="137"/>
     <lemma form="pogrezniti" freq="137"/>
     <lemma form="prijezditi" freq="137"/>
     <lemma form="izogibati" freq="137"/>
     <lemma form="prestreči" freq="137"/>
     <lemma form="izbirati" freq="136"/>
     <lemma form="pokoriti" freq="136"/>
     <lemma form="pogoditi" freq="136"/>
     <lemma form="zaihteti" freq="136"/>
     <lemma form="božati" freq="136"/>
     <lemma form="prizadevati" freq="136"/>
     <lemma form="poprijeti" freq="135"/>
     <lemma form="prezirati" freq="135"/>
     <lemma form="podpisati" freq="135"/>
     <lemma form="poleči" freq="135"/>
     <lemma form="olajšati" freq="135"/>
     <lemma form="tlačiti" freq="134"/>
     <lemma form="sikniti" freq="134"/>
     <lemma form="ogniti" freq="134"/>
     <lemma form="zatrepetati" freq="134"/>
     <lemma form="postavljati" freq="134"/>
     <lemma form="odzvati" freq="134"/>
     <lemma form="iznenaditi" freq="134"/>
     <lemma form="opravičiti" freq="134"/>
     <lemma form="režati" freq="134"/>
     <lemma form="izkusiti" freq="133"/>
     <lemma form="spreti" freq="133"/>
     <lemma form="poganjati" freq="133"/>
     <lemma form="vzravnati" freq="133"/>
     <lemma form="izvirati" freq="133"/>
     <lemma form="odgnati" freq="132"/>
     <lemma form="osvoboditi" freq="132"/>
     <lemma form="popustiti" freq="132"/>
     <lemma form="zasaditi" freq="132"/>
     <lemma form="sekati" freq="132"/>
     <lemma form="pretrpeti" freq="132"/>
     <lemma form="cveteti" freq="132"/>
     <lemma form="poljubovati" freq="132"/>
     <lemma form="potožiti" freq="131"/>
     <lemma form="pihati" freq="131"/>
     <lemma form="poizkusiti" freq="131"/>
     <lemma form="možiti" freq="130"/>
     <lemma form="zatreti" freq="130"/>
     <lemma form="zrasti" freq="130"/>
     <lemma form="snovati" freq="130"/>
     <lemma form="lomiti" freq="130"/>
     <lemma form="pokati" freq="130"/>
     <lemma form="posoditi" freq="130"/>
     <lemma form="izgubljati" freq="130"/>
     <lemma form="sprožiti" freq="130"/>
     <lemma form="blagosloviti" freq="129"/>
     <lemma form="dognati" freq="129"/>
     <lemma form="prerokovati" freq="129"/>
     <lemma form="omahovati" freq="129"/>
     <lemma form="ideti" freq="129"/>
     <lemma form="zateči" freq="128"/>
     <lemma form="uresničiti" freq="128"/>
     <lemma form="tolmačiti" freq="128"/>
     <lemma form="zmajati" freq="128"/>
     <lemma form="tavati" freq="128"/>
     <lemma form="udarjati" freq="128"/>
     <lemma form="stegniti" freq="128"/>
     <lemma form="zaboleti" freq="128"/>
     <lemma form="odjezditi" freq="128"/>
     <lemma form="plesti" freq="127"/>
     <lemma form="ugrabiti" freq="127"/>
     <lemma form="gosti" freq="127"/>
     <lemma form="treniti" freq="127"/>
     <lemma form="utoniti" freq="127"/>
     <lemma form="dohajati" freq="126"/>
     <lemma form="voliti" freq="126"/>
     <lemma form="poteči" freq="126"/>
     <lemma form="priporočati" freq="126"/>
     <lemma form="spadati" freq="126"/>
     <lemma form="vriskati" freq="126"/>
     <lemma form="razločevati" freq="126"/>
     <lemma form="opustiti" freq="126"/>
     <lemma form="sleči" freq="126"/>
     <lemma form="prehiteti" freq="126"/>
     <lemma form="ujemati" freq="125"/>
     <lemma form="premeriti" freq="125"/>
     <lemma form="razjeziti" freq="125"/>
     <lemma form="bliskati" freq="125"/>
     <lemma form="oživeti" freq="125"/>
     <lemma form="spuščati" freq="125"/>
     <lemma form="poučiti" freq="124"/>
     <lemma form="nakloniti" freq="124"/>
     <lemma form="prihraniti" freq="124"/>
     <lemma form="zgrešiti" freq="124"/>
     <lemma form="zroč" freq="124"/>
     <lemma form="razburjati" freq="124"/>
     <lemma form="zazibati" freq="124"/>
     <lemma form="došeti" freq="124"/>
     <lemma form="prenočiti" freq="124"/>
     <lemma form="splezati" freq="124"/>
     <lemma form="vdreti" freq="124"/>
     <lemma form="sklicati" freq="123"/>
     <lemma form="ovirati" freq="123"/>
     <lemma form="poizvedovati" freq="123"/>
     <lemma form="javkati" freq="123"/>
     <lemma form="dolžiti" freq="123"/>
     <lemma form="greti" freq="122"/>
     <lemma form="obliti" freq="122"/>
     <lemma form="odsevati" freq="122"/>
     <lemma form="usmrtiti" freq="122"/>
     <lemma form="začenjati" freq="122"/>
     <lemma form="razkladati" freq="121"/>
     <lemma form="najeti" freq="121"/>
     <lemma form="popeljati" freq="121"/>
     <lemma form="vztrepetati" freq="121"/>
     <lemma form="zavrteti" freq="121"/>
     <lemma form="giniti" freq="121"/>
     <lemma form="prodirati" freq="121"/>
     <lemma form="pripogniti" freq="121"/>
     <lemma form="poroditi" freq="120"/>
     <lemma form="počenjati" freq="120"/>
     <lemma form="krčiti" freq="120"/>
     <lemma form="uganjati" freq="120"/>
     <lemma form="nuditi" freq="120"/>
     <lemma form="presenetiti" freq="120"/>
     <lemma form="zdrzniti" freq="120"/>
     <lemma form="pomeriti" freq="119"/>
     <lemma form="vzprejeti" freq="119"/>
     <lemma form="potikati" freq="119"/>
     <lemma form="drhteti" freq="119"/>
     <lemma form="umejati" freq="118"/>
     <lemma form="nagajati" freq="118"/>
     <lemma form="zasačiti" freq="118"/>
     <lemma form="domišljati" freq="118"/>
     <lemma form="zažgati" freq="118"/>
     <lemma form="zmračiti" freq="118"/>
     <lemma form="zavreči" freq="118"/>
     <lemma form="trebati" freq="118"/>
     <lemma form="slaviti" freq="118"/>
     <lemma form="potopiti" freq="118"/>
     <lemma form="zboleti" freq="117"/>
     <lemma form="izražati" freq="117"/>
     <lemma form="švigniti" freq="117"/>
     <lemma form="zmerjati" freq="117"/>
     <lemma form="utrgati" freq="117"/>
     <lemma form="odpuščati" freq="117"/>
     <lemma form="splaziti" freq="117"/>
     <lemma form="vznemiriti" freq="117"/>
     <lemma form="vzrasti" freq="116"/>
     <lemma form="natočiti" freq="116"/>
     <lemma form="pozvedeti" freq="116"/>
     <lemma form="zadremati" freq="116"/>
     <lemma form="dohiteti" freq="116"/>
     <lemma form="zavezati" freq="115"/>
     <lemma form="preobleči" freq="115"/>
     <lemma form="podpreti" freq="115"/>
     <lemma form="posedati" freq="115"/>
     <lemma form="ponašati" freq="115"/>
     <lemma form="pogubiti" freq="115"/>
     <lemma form="žvižgati" freq="115"/>
     <lemma form="plakati" freq="115"/>
     <lemma form="uslišati" freq="115"/>
     <lemma form="obiskovati" freq="115"/>
     <lemma form="odstraniti" freq="115"/>
     <lemma form="gnesti" freq="115"/>
     <lemma form="pritoževati" freq="115"/>
     <lemma form="odleteti" freq="114"/>
     <lemma form="sprijazniti" freq="114"/>
     <lemma form="izplačati" freq="114"/>
     <lemma form="posnemati" freq="114"/>
     <lemma form="zavihteti" freq="114"/>
     <lemma form="posmejati" freq="114"/>
     <lemma form="ukrotiti" freq="114"/>
     <lemma form="klati" freq="114"/>
     <lemma form="zvrniti" freq="113"/>
     <lemma form="zatajiti" freq="113"/>
     <lemma form="razjokati" freq="113"/>
     <lemma form="rediti" freq="113"/>
     <lemma form="žgati" freq="113"/>
     <lemma form="razodevati" freq="113"/>
     <lemma form="tirati" freq="113"/>
     <lemma form="naročati" freq="113"/>
     <lemma form="sejati" freq="112"/>
     <lemma form="zazveneti" freq="112"/>
     <lemma form="onemoči" freq="112"/>
     <lemma form="prebirati" freq="111"/>
     <lemma form="speči" freq="111"/>
     <lemma form="grešiti" freq="111"/>
     <lemma form="veslati" freq="111"/>
     <lemma form="uhajati" freq="111"/>
     <lemma form="izprositi" freq="111"/>
     <lemma form="dotikati" freq="111"/>
     <lemma form="predramiti" freq="111"/>
     <lemma form="privzdigniti" freq="111"/>
     <lemma form="zavijati" freq="110"/>
     <lemma form="izdajati" freq="110"/>
     <lemma form="preudariti" freq="110"/>
     <lemma form="odjahati" freq="110"/>
     <lemma form="zakrohotati" freq="110"/>
     <lemma form="dogoditi" freq="110"/>
     <lemma form="napenjati" freq="110"/>
     <lemma form="stemniti" freq="109"/>
     <lemma form="mračiti" freq="109"/>
     <lemma form="izpovedati" freq="109"/>
     <lemma form="sikati" freq="109"/>
     <lemma form="pospešiti" freq="109"/>
     <lemma form="žugati" freq="109"/>
     <lemma form="vrstiti" freq="109"/>
     <lemma form="plezati" freq="109"/>
     <lemma form="muzati" freq="109"/>
     <lemma form="krohotati" freq="109"/>
     <lemma form="pehati" freq="109"/>
     <lemma form="zaslediti" freq="108"/>
     <lemma form="zbati" freq="108"/>
     <lemma form="dopuščati" freq="108"/>
     <lemma form="tekati" freq="108"/>
     <lemma form="grmeti" freq="108"/>
     <lemma form="zadaviti" freq="108"/>
     <lemma form="ugrizniti" freq="108"/>
     <lemma form="razvijati" freq="108"/>
     <lemma form="rojiti" freq="108"/>
     <lemma form="ukloniti" freq="108"/>
     <lemma form="doliti" freq="107"/>
     <lemma form="priporočiti" freq="107"/>
     <lemma form="pomenkovati" freq="107"/>
     <lemma form="prirediti" freq="107"/>
     <lemma form="pljuniti" freq="107"/>
     <lemma form="zabraniti" freq="107"/>
     <lemma form="koprneti" freq="107"/>
     <lemma form="popisati" freq="106"/>
     <lemma form="zmoči" freq="106"/>
     <lemma form="zajeti" freq="106"/>
     <lemma form="raniti" freq="106"/>
     <lemma form="zagrabiti" freq="106"/>
     <lemma form="naliti" freq="105"/>
     <lemma form="pregledovati" freq="105"/>
     <lemma form="priznavati" freq="105"/>
     <lemma form="omamiti" freq="105"/>
     <lemma form="izneveriti" freq="105"/>
     <lemma form="iztakniti" freq="104"/>
     <lemma form="žeti" freq="104"/>
     <lemma form="ovaditi" freq="104"/>
     <lemma form="zagotoviti" freq="104"/>
     <lemma form="privabiti" freq="104"/>
     <lemma form="zabliskati" freq="103"/>
     <lemma form="potipati" freq="103"/>
     <lemma form="podirati" freq="103"/>
     <lemma form="nalagati" freq="103"/>
     <lemma form="vihrati" freq="103"/>
     <lemma form="zlagati" freq="103"/>
     <lemma form="omenjati" freq="103"/>
     <lemma form="navduševati" freq="103"/>
     <lemma form="potreti" freq="102"/>
     <lemma form="osvojiti" freq="102"/>
     <lemma form="provzročiti" freq="102"/>
     <lemma form="užaliti" freq="102"/>
     <lemma form="strinjati" freq="102"/>
     <lemma form="obsevati" freq="102"/>
     <lemma form="upasti" freq="102"/>
     <lemma form="daviti" freq="102"/>
     <lemma form="vzdržati" freq="102"/>
     <lemma form="izbrisati" freq="102"/>
     <lemma form="oživiti" freq="102"/>
     <lemma form="obsojati" freq="101"/>
     <lemma form="osrečiti" freq="101"/>
     <lemma form="donašati" freq="101"/>
     <lemma form="vihteti" freq="101"/>
     <lemma form="posvariti" freq="101"/>
     <lemma form="nasprotovati" freq="101"/>
     <lemma form="zlomiti" freq="101"/>
     <lemma form="poskrbeti" freq="101"/>
     <lemma form="premoči" freq="101"/>
     <lemma form="zadreti" freq="101"/>
     </frequencies>
